setup.py
groundstation/__init__.py
groundstation/broadcast_announcer.py
groundstation/broadcast_discoverer.py
groundstation/broadcast_event.py
groundstation/config.py
groundstation/deferred.py
groundstation/fs_watcher.py
groundstation/gizmo_factory.py
groundstation/gref.py
groundstation/logger.py
groundstation/node.py
groundstation/packed_keys.py
groundstation/peer_socket.py
groundstation/peer_socket_pool.py
groundstation/request_registry.py
groundstation/settings.py
groundstation/station.py
groundstation/stream_client.py
groundstation/stream_listener.py
groundstation.egg-info/PKG-INFO
groundstation.egg-info/SOURCES.txt
groundstation.egg-info/dependency_links.txt
groundstation.egg-info/top_level.txt
test/test_all_stores.py
test/test_crypto_rsaadaptor.py
test/test_db_hash_handler.py
test/test_describechannels_handler.py
test/test_describeobjects_handler.py
test/test_fetchobject_handler.py
test/test_gizmo_request.py
test/test_gref.py
test/test_gref_marshall.py
test/test_listallchannels_handler.py
test/test_listallobjects_handler.py
test/test_newobject_handler.py
test/test_notification_integration.py
test/test_object_factory.py
test/test_peer_socket_pool.py
test/test_request_registry.py
test/test_root_object.py
test/test_station.py
test/test_station_deferred.py
test/test_station_integration.py
test/test_station_object_watcher.py
test/test_terminate_handler.py
test/test_transfer_handler.py
test/test_update_object.py
test/test_utils.py