Metadata-Version: 1.0
Name: groundstation
Version: 0.0.0
Summary: A decentralised git syncronisation engine
Home-page: https://github.com/richo/groundstation
Author: Richo Healey
Author-email: richo@psych0tik.net
License: MIT
Platform: UNKNOWN
